pipeline_caller
