Metadata-Version: 1.1
Name: ITU-Turkish-NLP-Pipeline-Caller
Version: 2.2.0
Summary: A wrapper tool to use ITU Turkish NLP Pipeline API
Home-page: https://github.com/ferittuncer/ITU-Turkish-NLP-Pipeline-Caller
Author: Ferit Tunçer
Author-email: ferit.tuncer@autistici.org
License: GPLv2
Keywords: ITU Turkish NLP Pipeline
Platform: UNKNOWN
Classifier: Development Status :: 5 - Production/Stable
Classifier: License :: OSI Approved :: GNU General Public License v2 (GPLv2)
Classifier: Topic :: Text Processing :: Linguistic
Classifier: Natural Language :: Turkish
Classifier: Programming Language :: Python :: 3
